[
    {
        "id": 1,
        "name": "profileAttributes",
        "description": "",
        "label": "",
        "suffix": "_2608",
        "metadata": {
            "title": "profileAttributes",
            "readAccess": "public",
            "appliesTo": [
                "profile"
            ],
            "id": 1,
            "suffix": "_2608",
            "description": "",
            "fields": [
                {
                    "visibility": "public",
                    "tableId": 1,
                    "tableName": "profileAttributes",
                    "tableSuffix": "_2608",
                    "title": "profileIcon",
                    "label": "Profile Icon",
                    "description": "",
                    "fieldType": "text",
                    "color": "rgb(NaN, NaN, NaN)",
                    "searchability": "public",
                    "editability": "registered",
                    "fieldTextOptions": {
                        "textType": "input",
                        "inputOptions": {
                            "buildAutocomplete": false,
                            "requireModeration": false,
                            "limitMaxChars": 0,
                            "limitMaxWords": 0,
                            "allowHtml": false,
                            "allowMedia": true,
                            "allowLinks": true
                        },
                        "listOptions": {
                            "takeSugesstions": true,
                            "buildTree": false,
                            "iconize": false,
                            "colorize": false
                        }
                    },
                    "allowMultiple": false
                },
                {
                    "visibility": "public",
                    "tableId": 1,
                    "tableName": "profileAttributes",
                    "tableSuffix": "_2608",
                    "title": "email",
                    "label": "Email",
                    "description": "",
                    "fieldType": "text",
                    "color": "rgb(undefined, undefined, undefined)",
                    "searchability": "public",
                    "editability": "registered",
                    "fieldTextOptions": {
                        "textType": "input",
                        "inputOptions": {
                            "buildAutocomplete": false,
                            "requireModeration": false,
                            "limitMaxChars": 0,
                            "limitMaxWords": 0,
                            "allowHtml": false,
                            "allowMedia": true,
                            "allowLinks": true
                        },
                        "listOptions": {
                            "takeSugesstions": true,
                            "buildTree": false,
                            "iconize": false,
                            "colorize": false
                        }
                    },
                    "allowMultiple": false
                }
            ]
        }
    },
    {
        "id": 2,
        "name": "eventAttributes",
        "description": "",
        "label": "",
        "suffix": "_3357",
        "metadata": {
            "title": "eventAttributes",
            "readAccess": "public",
            "appliesTo": [
                "event"
            ],
            "id": 2,
            "suffix": "_3357",
            "description": "",
            "fields": [
                {
                    "visibility": "public",
                    "tableId": 2,
                    "tableName": "eventAttributes",
                    "tableSuffix": "_3357",
                    "title": "eventIcon",
                    "label": "Event Icon",
                    "description": "",
                    "fieldType": "text",
                    "color": "rgb(NaN, NaN, NaN)",
                    "searchability": "public",
                    "editability": "registered",
                    "fieldTextOptions": {
                        "textType": "input",
                        "inputOptions": {
                            "buildAutocomplete": false,
                            "requireModeration": false,
                            "limitMaxChars": 0,
                            "limitMaxWords": 0,
                            "allowHtml": false,
                            "allowMedia": true,
                            "allowLinks": true
                        },
                        "listOptions": {
                            "takeSugesstions": true,
                            "buildTree": false,
                            "iconize": false,
                            "colorize": false
                        }
                    },
                    "allowMultiple": false
                },
                {
                    "visibility": "public",
                    "tableId": 2,
                    "tableName": "eventAttributes",
                    "tableSuffix": "_3357",
                    "title": "tags",
                    "label": "Tags",
                    "description": "",
                    "fieldType": "text",
                    "color": "rgb(undefined, undefined, undefined)",
                    "searchability": "public",
                    "editability": "registered",
                    "fieldTextOptions": {
                        "textType": "input",
                        "inputOptions": {
                            "buildAutocomplete": false,
                            "requireModeration": false,
                            "limitMaxChars": 0,
                            "limitMaxWords": 0,
                            "allowHtml": false,
                            "allowMedia": true,
                            "allowLinks": true
                        },
                        "listOptions": {
                            "takeSugesstions": true,
                            "buildTree": false,
                            "iconize": false,
                            "colorize": false
                        }
                    },
                    "allowMultiple": true
                },
                {
                    "visibility": "public",
                    "tableId": 2,
                    "tableName": "eventAttributes",
                    "tableSuffix": "_3357",
                    "title": "eventDate",
                    "label": "Event Date",
                    "description": "",
                    "fieldType": "text",
                    "color": "rgb(NaN, NaN, NaN)",
                    "searchability": "public",
                    "editability": "registered",
                    "fieldTextOptions": {
                        "textType": "input",
                        "inputOptions": {
                            "buildAutocomplete": false,
                            "requireModeration": false,
                            "limitMaxChars": 0,
                            "limitMaxWords": 0,
                            "allowHtml": false,
                            "allowMedia": true,
                            "allowLinks": true
                        },
                        "listOptions": {
                            "takeSugesstions": true,
                            "buildTree": false,
                            "iconize": false,
                            "colorize": false
                        }
                    },
                    "allowMultiple": false
                },
                {
                    "visibility": "public",
                    "tableId": 2,
                    "tableName": "eventAttributes",
                    "tableSuffix": "_3357",
                    "title": "eventTime",
                    "label": "Event Time",
                    "description": "",
                    "fieldType": "text",
                    "color": "rgb(undefined, undefined, undefined)",
                    "searchability": "public",
                    "editability": "registered",
                    "fieldTextOptions": {
                        "textType": "input",
                        "inputOptions": {
                            "buildAutocomplete": false,
                            "requireModeration": false,
                            "limitMaxChars": 0,
                            "limitMaxWords": 0,
                            "allowHtml": false,
                            "allowMedia": true,
                            "allowLinks": true
                        },
                        "listOptions": {
                            "takeSugesstions": true,
                            "buildTree": false,
                            "iconize": false,
                            "colorize": false
                        }
                    },
                    "allowMultiple": false
                },
                {
                    "visibility": "public",
                    "tableId": 2,
                    "tableName": "eventAttributes",
                    "tableSuffix": "_3357",
                    "title": "startDate",
                    "label": "Start Date",
                    "description": "",
                    "fieldType": "text",
                    "color": "rgb(undefined, undefined, undefined)",
                    "searchability": "public",
                    "editability": "registered",
                    "fieldTextOptions": {
                        "textType": "input",
                        "inputOptions": {
                            "buildAutocomplete": false,
                            "requireModeration": false,
                            "limitMaxChars": 0,
                            "limitMaxWords": 0,
                            "allowHtml": false,
                            "allowMedia": true,
                            "allowLinks": true
                        },
                        "listOptions": {
                            "takeSugesstions": true,
                            "buildTree": false,
                            "iconize": false,
                            "colorize": false
                        }
                    },
                    "allowMultiple": false
                },
                {
                    "visibility": "public",
                    "tableId": 2,
                    "tableName": "eventAttributes",
                    "tableSuffix": "_3357",
                    "title": "endDate",
                    "label": "End Date",
                    "description": "",
                    "fieldType": "text",
                    "color": "rgb(undefined, undefined, undefined)",
                    "searchability": "public",
                    "editability": "registered",
                    "fieldTextOptions": {
                        "textType": "input",
                        "inputOptions": {
                            "buildAutocomplete": false,
                            "requireModeration": false,
                            "limitMaxChars": 0,
                            "limitMaxWords": 0,
                            "allowHtml": false,
                            "allowMedia": true,
                            "allowLinks": true
                        },
                        "listOptions": {
                            "takeSugesstions": true,
                            "buildTree": false,
                            "iconize": false,
                            "colorize": false
                        }
                    },
                    "allowMultiple": false
                }
            ]
        }
    }
]