[

	{
		"itemType": "ProjectHub.profile",
		"itemId": "527",
		"name": "ProjectHub.profile: Hello World",
		"description": "Test Test",
		"metadata": "{}",
		"createdDate": "2018-01-15 23:55:02",
		"modifiedDate": "2018-01-15 23:55:02",
		"readAccess": "public",
		"writeAccess": "registered",

		"type": "ProjectHub.profile"
	}, {

		"itemType": "ProjectHub.profile",
		"itemId": "527",
		"name": "ProjectHub.project: Hello World",
		"description": "Test Test",
		"metadata": "{}",
		"createdDate": "2018-01-15 23:55:02",
		"modifiedDate": "2018-01-15 23:55:02",
		"readAccess": "public",
		"writeAccess": "registered",

		"type": "ProjectHub.project"
	}, {

		"itemType": "ProjectHub.profile",
		"itemId": "527",
		"name": "ProjectHub.event: Hello World",
		"description": "Test Test",
		"metadata": "{}",
		"createdDate": "2018-01-15 23:55:02",
		"modifiedDate": "2018-01-15 23:55:02",
		"readAccess": "public",
		"writeAccess": "registered",

		"type": "ProjectHub.event"
	}, {

		"itemType": "ProjectHub.profile",
		"itemId": "527",
		"name": "ProjectHub.connection: Hello World",
		"description": "Test Test",
		"metadata": "{}",
		"createdDate": "2018-01-15 23:55:02",
		"modifiedDate": "2018-01-15 23:55:02",
		"readAccess": "public",
		"writeAccess": "registered",

		"type": "ProjectHub.connection"
	}, {

		"itemType": "ProjectHub.profile",
		"itemId": "527",
		"name": "ProjectHub.event: Hello World",
		"description": "Test Test",
		"metadata": "{}",
		"createdDate": "2018-01-15 23:55:02",
		"modifiedDate": "2018-01-15 23:55:02",
		"readAccess": "public",
		"writeAccess": "registered",

		"type": "ProjectHub.event"
	}, {

		"itemType": "ProjectHub.profile",
		"itemId": "527",
		"name": "ProjectHub.request: Hello World",
		"description": "Test Test",
		"metadata": "{}",
		"createdDate": "2018-01-15 23:55:02",
		"modifiedDate": "2018-01-15 23:55:02",
		"readAccess": "public",
		"writeAccess": "registered",

		"type": "ProjectHub.request"
	}, {

		"itemType": "ProjectHub.profile",
		"itemId": "527",
		"name": "ProjectHub.event: Hello World",
		"description": "Test Test",
		"metadata": "{}",
		"createdDate": "2018-01-15 23:55:02",
		"modifiedDate": "2018-01-15 23:55:02",
		"readAccess": "public",
		"writeAccess": "registered",

		"type": "ProjectHub.event"
	}, {

		"itemType": "ProjectHub.profile",
		"itemId": "527",
		"name": "ProjectHub.event: Hello World",
		"description": "Test Test",
		"metadata": "{}",
		"createdDate": "2018-01-15 23:55:02",
		"modifiedDate": "2018-01-15 23:55:02",
		"readAccess": "public",
		"writeAccess": "registered",

		"type": "ProjectHub.event"
	}


]